{
  "headers": {
    "x-amz-id-2": "tbI4c8TN/xQEe6IW/ouK/Bxl3O9Y8W/49M1HP1kwnyglC2KlZ2uc90Mvz/jpUaeGRzThXAHnM0A=",
    "x-amz-request-id": "0JAZ7C6T4Q8NSM14",
    "x-amz-version-id": "a0r5Qd_ub6.ZAsqAuYbqa1HFkd42c7Uh",
    "access-control-allow-origin": "*",
    "content-type": "application/javascript",
    "server": "deploy/europe-west1-b",
    "date": "Tue, 16 Nov 2021 23:07:41 GMT",
    "last-modified": "Mon, 09 Nov 2020 01:50:12 GMT",
    "cache-control": "public, max-age=31536000, immutable",
    "etag": "\"0db6f018981d8bfa5c188d5db0c0dd56\"",
    "content-length": "45688"
  },
  "url": "https://deno.land/x/yargs_parser@v20.2.4-deno/build/lib/yargs-parser.js"
}