{
  "headers": {
    "cache-control": "public, max-age=31536000, immutable",
    "server": "deploy/europe-west1-b",
    "x-amz-id-2": "fB95dAklXMuVL6nHAU2ipW7MQUSikJv3UHzip2FVvD3v/iOIhzVOFtSWv4SvY2vhiuhi2+0KPzw=",
    "x-amz-version-id": "n88lws2cpGSruuiMFFl2cTF0ehH.68u9",
    "date": "Tue, 16 Nov 2021 23:07:41 GMT",
    "content-type": "application/javascript",
    "etag": "\"013c4bda8ae279796debc40b26301291\"",
    "last-modified": "Sun, 08 Nov 2020 23:59:36 GMT",
    "content-length": "1011",
    "x-amz-request-id": "0JAM1P93JFCVNR79",
    "access-control-allow-origin": "*"
  },
  "url": "https://deno.land/x/cliui@v7.0.4-deno/build/lib/string-utils.js"
}