{
  "headers": {
    "date": "Tue, 16 Nov 2021 23:07:41 GMT",
    "cache-control": "public, max-age=31536000, immutable",
    "server": "deploy/europe-west1-b",
    "access-control-allow-origin": "*",
    "x-amz-request-id": "0JAMPG9PCYNP9RTN",
    "content-length": "181",
    "last-modified": "Mon, 15 Nov 2021 13:49:18 GMT",
    "x-amz-id-2": "sqjrPH+WWlFxFnv0v6jRAJ9nnVMkz30GuvN8cpH1SxBrj/41fFUXpbSjwnGFbQ+X+z4KVJhFk6I=",
    "x-amz-version-id": "cSrxwQ7M1KoSasvVj2gzeLSyfwcsE1IF",
    "etag": "\"87f0f096428e7141fd979ec3d9f2679c\"",
    "content-type": "application/typescript; charset=utf-8"
  },
  "url": "https://deno.land/x/shell_stream@v0.1.12/startpoints/from_string.ts"
}