{
  "headers": {
    "content-type": "application/typescript; charset=utf-8",
    "etag": "\"08c8a67c0e71c676585405038745cfb5\"",
    "last-modified": "Sat, 05 Sep 2020 02:33:55 GMT",
    "x-amz-id-2": "zOwqW9APIQmS+KO3UZGdSHBKIIhtEgKtT3QXMatunl0XI0wXULrGwTpDjtFR86xN32YkNO4S2Eg=",
    "content-length": "645",
    "x-amz-version-id": "null",
    "access-control-allow-origin": "*",
    "cache-control": "public, max-age=31536000, immutable",
    "date": "Tue, 16 Nov 2021 23:07:41 GMT",
    "x-amz-request-id": "0JARCHXX7F1Z8RS8",
    "server": "deploy/europe-west1-b"
  },
  "url": "https://deno.land/x/y18n@v5.0.0-deno/build/lib/index.d.ts"
}